LICENSE
MANIFEST.in
README.md
pyproject.toml
src/maritime_schema/__init__.py
src/maritime_schema/api.py
src/maritime_schema/py.typed
src/maritime_schema.egg-info/PKG-INFO
src/maritime_schema.egg-info/SOURCES.txt
src/maritime_schema.egg-info/dependency_links.txt
src/maritime_schema.egg-info/entry_points.txt
src/maritime_schema.egg-info/requires.txt
src/maritime_schema.egg-info/top_level.txt
src/maritime_schema/cli/__init__.py
src/maritime_schema/cli/publish_schema.py
src/maritime_schema/types/__init__.py
src/maritime_schema/types/caga.py
src/maritime_schema/types/caga_examples.py
src/maritime_schema/utils/__init__.py
src/maritime_schema/utils/logging.py
src/maritime_schema/utils/publish.py
src/maritime_schema/utils/strings.py
tests/test_api.py