Metadata-Version: 2.2
Name: maritime-schema
Version: 0.0.7
Summary: Python data classes and JSON schemata for maritime traffic scenarios.
Author-email: Minos Hemrich <minos.hemrich@dnv.com>, Tom Arne Pedersen <tom.arne.pedersen@dnv.com>
Maintainer-email: Claas Rostock <claas.rostock@dnv.com>
License: MIT License
Project-URL: Homepage, https://github.com/dnv-opensource/maritime-schema
Project-URL: Documentation, https://dnv-opensource.github.io/maritime-schema/README.html
Project-URL: Repository, https://github.com/dnv-opensource/maritime-schema.git
Project-URL: Issues, https://github.com/dnv-opensource/maritime-schema/issues
Project-URL: Changelog, https://github.com/dnv-opensource/maritime-schema/blob/main/CHANGELOG.md
Classifier: Development Status :: 3 - Alpha
Classifier: License :: OSI Approved :: MIT License
Classifier: Programming Language :: Python :: 3.9
Classifier: Programming Language :: Python :: 3.10
Classifier: Programming Language :: Python :: 3.11
Classifier: Programming Language :: Python :: 3.12
Classifier: Operating System :: Microsoft :: Windows
Classifier: Operating System :: POSIX :: Linux
Classifier: Operating System :: MacOS
Classifier: Environment :: Console
Classifier: Intended Audience :: Developers
Classifier: Intended Audience :: Science/Research
Classifier: Topic :: Scientific/Engineering
Classifier: Topic :: Software Development :: Libraries :: Python Modules
Requires-Python: >=3.9
License-File: LICENSE
Requires-Dist: pydantic>=2.6
Requires-Dist: json-schema-for-humans>=0.4.7
Requires-Dist: dictIO>=0.3.3
Requires-Dist: pyproj>=3.6.1
